[
  {
    "id": 0,
    "title": "Происхождение",
    "author": "Дэн Браун",
    "image": "https://images.ua.prom.st/1032730593_w640_h640_proishozhdenie-den-braun.jpg",
    "price": 710,
    "rating": 3
  },
  {
    "id": 1,
    "title": "1984",
    "author": "Джордж Оруэлл",
    "image": "https://knigopoisk.com/files/2016/06/kniga-Glotnut-vozduha-Dzhordzh-Oruell.jpg",
    "price": 415,
    "rating": 5
  },
  {
    "id": 2,
    "title": "Девушка в тумане",
    "author": "Донато Карризи",
    "image": "https://cdn1.ozone.ru/s3/multimedia-6/c650/6006165150.jpg",
    "price": 464,
    "rating": 4
  },
  {
    "id": 3,
    "title": "Империя должна умереть",
    "author": "Михаил Зыгарь",
    "image": "https://www.alpinabook.ru/upload/resize_cache/iblock/235/380_567_1/2354cac6fff06974bdb7b63986b97a67.jpg",
    "price": 741,
    "rating": 3
  },
  {
    "id": 4,
    "title": "Земное притяжение",
    "author": "Татьяна Устинова",
    "image": "https://cdn.eksmo.ru/v2/ITD000000000873502/COVER/cover1__w600.jpg",
    "price": 317,
    "rating": 1
  },
  {
    "id": 5,
    "title": "Зулейха открывает глаза",
    "author": "Гузель Яхина",
    "image": "https://i2.rozetka.ua/goods/7181558/52951866_images_7181558610.jpg",
    "price": 254,
    "rating": 0
  },
  {
    "id": 6,
    "title": "Очаровательный кишечник. Как самый могущественный орган управляет нами",
    "author": "Джулия Эндерс",
    "image": "https://www.podpisnie.ru/upload/iblock/1f9/1f9440de9e80281e983133bee5e4467f.jpg",
    "price": 573,
    "rating": 4
  },
  {
    "id": 7,
    "title": "iPhuck 10",
    "author": "Виктор Пелевин",
    "image": "https://cdn.27.ua/799/9b/71/564081_9.jpeg",
    "price": 246,
    "rating": 0
  },
  {
    "id": 8,
    "title": "7 навыков высокоэффективных людей: Мощные...",
    "author": "Стивен Кови",
    "image": "https://img.yakaboo.ua/media/catalog/product/cache/1/image/398x565/234c7c011ba026e66d29567e1be1d1f7/i/m/img337_40.jpg",
    "price": 347,
    "rating": 5
  },
  {
    "id": 9,
    "title": "Девушка во льду",
    "author": "Роберт Брындза",
    "image": "https://img.yakaboo.ua/media/catalog/product/cache/1/image/398x565/234c7c011ba026e66d29567e1be1d1f7/c/o/cover1_398_5.jpg",
    "price": 882,
    "rating": 2
  },
  {
    "id": 10,
    "title": "Магия утра. Как первый час дня определяет ваш успех",
    "author": "Хэл Элрод",
    "image": "https://www.mann-ivanov-ferber.ru/assets/images/covers/53/16753/1.00x-thumb.png",
    "price": 829,
    "rating": 1
  },
  {
    "id": 11,
    "title": "Азиатская европеизация. История Российского государства. Царь Петр...",
    "author": "Борис Акунин",
    "image": "https://www.rulit.me/data/programs/images/pervoistochniki-povest-vremennyh-let-galicko-volynskaya-leto_377051.jpg",
    "price": 389,
    "rating": 2
  },
  {
    "id": 12,
    "title": "Ведьмак (сборник)",
    "author": "Анджей Сапковский",
    "image": "https://cdn1.ozone.ru/multimedia/c650/1021391446.jpg",
    "price": 424,
    "rating": 3
  },
  {
    "id": 13,
    "title": "Атлант расправил плечи",
    "author": "Айн Рэнд",
    "image": "https://images.ua.prom.st/1146834194_atlant-raspravil-plechi.jpg",
    "price": 157,
    "rating": 2
  },
  {
    "id": 14,
    "title": "Цена вопроса. Том 1",
    "author": "Александра Маринина",
    "image": "https://img.yakaboo.ua/media/catalog/product/cache/1/image/398x565/234c7c011ba026e66d29567e1be1d1f7/c/o/cover1__w600_336_126.jpg",
    "price": 664,
    "rating": 0
  },
  {
    "id": 15,
    "title": "Исчезнувшая",
    "author": "Гиллиан Флинн",
    "image": "https://upload.wikimedia.org/wikipedia/ru/1/1e/Gone_Girl_poster.jpg",
    "price": 476,
    "rating": 4
  },
  {
    "id": 17,
    "title": "Метро 2035",
    "author": "Дмитрий Глуховский",
    "image": "https://images.ua.prom.st/1628116384_w640_h640_dmitrij-gluhovskij-metro.jpg",
    "price": 837,
    "rating": 4
  },
  {
    "id": 18,
    "title": "Снеговик",
    "author": "Ю Несбё",
    "image": "https://images.ua.prom.st/1032735258_snegovik-mp-yu.jpg",
    "price": 796,
    "rating": 5
  },
  {
    "id": 19,
    "title": "Как тренировать память. Не думайте о памяти – лучше используйте ее на все сто!",
    "author": "Джонатан Хэнкок",
    "image": "https://www.knigikratko.ru/files/books_cover/251.png",
    "price": 399,
    "rating": 5
  }
]